[
    {
        "nombre": "Visual Studio Code",
        "icono": "/img/tecnologiaswebp/visualstudiocode.webp",
        "link": "https://code.visualstudio.com/"
    },
    {
        "nombre": "Android Studio",
        "icono": "/img/tecnologiaswebp/androidstudio.webp",
        "link": "https://developer.android.com/studio"
    },
    {
        "nombre": "PostgreSQL",
        "icono": "/img/tecnologiaswebp/postgresql.webp",
        "link": "https://www.postgresql.org/"
    },
    {
        "nombre": "phpMyAdmin",
        "icono": "/img/tecnologiaswebp/phpmyadmin.webp",
        "link": "https://www.phpmyadmin.net/"
    },
    {
        "nombre": "MySQL",
        "icono": "/img/tecnologiaswebp/mysql.webp",
        "link": "https://www.mysql.com/"
    },
    {
        "nombre": "React.js",
        "icono": "/img/tecnologiaswebp/reactjs.webp",
        "link": "https://reactjs.org/"
    },
    {
        "nombre": "Kotlin",
        "icono": "img/tecnologiaswebp/kotlin.webp",
        "link": "https://kotlinlang.org/"
    },
    {
        "nombre": "C",
        "icono": "img/tecnologiaswebp/c.webp",
        "link": "https://en.wikipedia.org/wiki/C_(programming_language)"
    },
    {
        "nombre": "C++",
        "icono": "img/tecnologiaswebp/c++.webp",
        "link": "https://isocpp.org/"
    },
    {
        "nombre": "Java",
        "icono": "img/tecnologiaswebp/java.webp",
        "link": "https://www.java.com/"
    },
    {
        "nombre": "JavaScript",
        "icono": "/img/tecnologiaswebp/javascript.webp",
        "link": "https://developer.mozilla.org/en-US/docs/Web/JavaScript"
    },
    {
        "nombre": "Boostrap",
        "icono": "/img/tecnologiaswebp/boostrap.webp",
        "link": "https://getbootstrap.com/"
    },
    {
        "nombre": "HTML",
        "icono": "/img/tecnologiaswebp/html.webp",
        "link": "https://developer.mozilla.org/en-US/docs/Web/HTML"
    },
    {
        "nombre": "CSS",
        "icono": "/img/tecnologiaswebp/css.webp",
        "link": "https://developer.mozilla.org/en-US/docs/Web/CSS"
    },
    {
        "nombre": "Github",
        "icono": "/img/tecnologiaswebp/github.webp",
        "link": "https://github.com/"
    },
    {
        "nombre": "Git",
        "icono": "/img/tecnologiaswebp/git.webp",
        "link": "https://git-scm.com/"
    },
    {
        "nombre": "Node.js",
        "icono": "/img/tecnologiaswebp/nodejs.svg",
        "link": "https://nodejs.org/"
    },
    {
        "nombre": "Express.js",
        "icono": "/img/tecnologiaswebp/express.webp",
        "link": "https://expressjs.com/"
    },
    {
        "nombre": "sequelize",
        "icono": "/img/tecnologiaswebp/sequelize.webp",
        "link": "https://sequelize.org/"
    },
    {
        "nombre": "Firebase",
        "icono": "/img/tecnologiaswebp/firebase.webp",
        "link": "https://firebase.google.com/"
    },
    {
        "nombre": "Figma",
        "icono": "/img/tecnologiaswebp/figma.webp",
        "link": "https://www.figma.com/"
    },
    {
        "nombre": "Fly.io",
        "icono": "/img/tecnologiaswebp/fly.io.webp",
        "link": "https://fly.io/"
    },
    {
        "nombre":"Neon.tech",
        "icono": "/img/tecnologiaswebp/neonserver.webp",
        "link": "https://neon.tech/"
    },
    {
        "nombre":"RapiApi",
        "icono": "/img/tecnologiaswebp/rapiapi.webp",
        "link": "https://rapidapi.com/"
    },
    {
        "nombre": "Axios",
        "icono": "/img/tecnologiaswebp/axios.webp",
        "link": "https://axios-http.com/"
    },
    {
        "nombre": "Ionic",
        "icono": "/img/tecnologiaswebp/ionic.webp",
        "link": "https://ionicframework.com/"
    }
]